typed_blockchaincom/__init__.py
typed_blockchaincom-0.1.0.dist-info/METADATA
typed_blockchaincom-0.1.0.dist-info/WHEEL
typed_blockchaincom-0.1.0.dist-info/top_level.txt
typed_blockchaincom-0.1.0.dist-info/RECORD
